README.rst
setup.py
autotweet_web/__init__.py
autotweet_web.egg-info/PKG-INFO
autotweet_web.egg-info/SOURCES.txt
autotweet_web.egg-info/dependency_links.txt
autotweet_web.egg-info/requires.txt
autotweet_web.egg-info/top_level.txt