Metadata-Version: 1.1
Name: autotweet-web
Version: 0.1.0
Summary: web instance for autotweet
Home-page: http://kjwon15.net/
Author: Kjwon15
Author-email: kjwonmail@gmail.com
License: UNKNOWN
Download-URL: https://github.com/Kjwon15/autotweet-web/releases
Platform: UNKNOWN
